src/__init__.py
src/snippet_keras_config.py
src/aiml/__init__.py
src/daqs/__init__.py
src/demo/__init__.py
src/prep/__init__.py
src/unst/__init__.py
src/util/__init__.py
EgC_Package-0.0.14.dist-info/License.txt
EgC_Package-0.0.14.dist-info/METADATA
EgC_Package-0.0.14.dist-info/WHEEL
EgC_Package-0.0.14.dist-info/top_level.txt
EgC_Package-0.0.14.dist-info/RECORD
