Metadata-Version: 2.1
Name: EgC-Package
Version: 0.0.14
Summary: A small example package from EGC
Home-page: https://github.com/EgC-Team/EngineeringGoesCloud
Author: EGC
Author-email: EGC@example.com
License: UNKNOWN
Platform: UNKNOWN
Classifier: Programming Language :: Python :: 3
Classifier: License :: OSI Approved :: MIT License
Classifier: Operating System :: OS Independent
Requires-Python: >=3.7
Requires-Dist: requests
Requires-Dist: keras
Provides-Extra: all
Requires-Dist: tsfresh ; extra == 'all'
Requires-Dist: scipy ; extra == 'all'
Requires-Dist: xlrd ; extra == 'all'
Requires-Dist: bitstruct ; extra == 'all'
Requires-Dist: pandas ; extra == 'all'
Requires-Dist: numpy (==1.19.3) ; extra == 'all'
Requires-Dist: seaborn ; extra == 'all'
Requires-Dist: asammdf ; extra == 'all'
Provides-Extra: asammdf
Requires-Dist: asammdf ; extra == 'asammdf'
Provides-Extra: bitstruct
Requires-Dist: bitstruct ; extra == 'bitstruct'
Provides-Extra: numpy
Requires-Dist: numpy (==1.19.3) ; extra == 'numpy'
Provides-Extra: pandas
Requires-Dist: pandas ; extra == 'pandas'
Provides-Extra: scipy
Requires-Dist: scipy ; extra == 'scipy'
Provides-Extra: seaborn
Requires-Dist: seaborn ; extra == 'seaborn'
Provides-Extra: tsfresh
Requires-Dist: tsfresh ; extra == 'tsfresh'
Provides-Extra: usecase1
Requires-Dist: xlrd ; extra == 'usecase1'
Requires-Dist: bitstruct ; extra == 'usecase1'
Requires-Dist: pandas ; extra == 'usecase1'
Requires-Dist: numpy (==1.19.3) ; extra == 'usecase1'
Requires-Dist: asammdf ; extra == 'usecase1'
Provides-Extra: usecase2
Requires-Dist: tsfresh ; extra == 'usecase2'
Requires-Dist: scipy ; extra == 'usecase2'
Requires-Dist: seaborn ; extra == 'usecase2'
Requires-Dist: xlrd ; extra == 'usecase2'
Provides-Extra: xlrd
Requires-Dist: xlrd ; extra == 'xlrd'
